drf_msgspec_json/__init__.py
drf_msgspec_json/parsers.py
drf_msgspec_json/renderers.py
drf_msgspec_json_renderer-0.2.0.dist-info/LICENSE
drf_msgspec_json_renderer-0.2.0.dist-info/WHEEL
drf_msgspec_json_renderer-0.2.0.dist-info/METADATA
drf_msgspec_json_renderer-0.2.0.dist-info/RECORD
