Metadata-Version: 2.1
Name: drf-msgspec-json-renderer
Version: 0.2.0
Summary: 
Author: Novitskii Aleksei
Author-email: mr.alexeynov95@gmail.com
Requires-Python: >=3.8,<4.0
Classifier: Programming Language :: Python :: 3
Classifier: Programming Language :: Python :: 3.8
Classifier: Programming Language :: Python :: 3.9
Classifier: Programming Language :: Python :: 3.10
Classifier: Programming Language :: Python :: 3.11
Requires-Dist: django (>=3.2,<4.0)
Requires-Dist: djangorestframework (>=3.14.0,<4.0.0)
Requires-Dist: msgspec (>=0.11.0,<0.12.0)
